{
  "items": [
    {
      "make": "Culpa",
      "model": "Aliquam",
      "price": 25436.72,
      "voted": 273,
      "rating": 2.244984739923738,
      "addedAt": "2020-06-11T16:46:09.864Z",
      "version": "Fugiat",
      "mileage": 12039,
      "carRegAt": "2016-03-28T22:42:01.000Z",
      "equipment": [
        "transmitter",
        "matrix",
        "driver",
        "hard drive",
        "circuit",
        "card",
        "alarm",
        "pixel",
        "circuit",
        "hard drive",
        "system",
        "monitor",
        "program",
        "capacitor",
        "application",
        "array",
        "feed",
        "application",
        "port"
      ],
      "description": "Quam est ea occaecati velit nam repellat. Et repudiandae voluptate occaecati est iusto explicabo rem et. Dolores sint ipsa voluptas.\n \rAutem temporibus molestias. Laudantium dolorum ipsa amet incidunt fuga vel reprehenderit. Qui necessitatibus ut impedit nostrum nihil voluptatibus ullam pariatur assumenda. Sed est quod asperiores ut praesentium sint earum. Qui facere nihil. In sint fugit rerum.\n \rEa enim ad ea. Autem beatae ipsam voluptatum aliquid. Est eum qui sequi nihil. Aut sequi sunt occaecati placeat aperiam sunt dolorem natus.",
      "sellerEmail": "Daren15@gmail.com",
      "sellerPhone": "+575 (85) 711-23-99",
      "sellerName": "Casimir Johnson",
      "sellerCompany": "Blanda and Sons",
      "id": 1,
      "imagesCount": 7
    },
    {
      "make": "Repudiandae",
      "model": "Consectetur",
      "price": 76284.2,
      "voted": 765,
      "rating": 4.083613032168339,
      "addedAt": "2020-06-11T19:28:36.701Z",
      "version": "Sunt",
      "mileage": 24747,
      "carRegAt": "2017-06-28T02:21:13.102Z",
      "equipment": [
        "bandwidth",
        "microchip",
        "firewall",
        "protocol",
        "matrix",
        "panel",
        "capacitor",
        "program",
        "matrix",
        "card",
        "firewall",
        "firewall",
        "bus",
        "alarm",
        "program",
        "sensor",
        "array",
        "monitor",
        "bandwidth",
        "microchip"
      ],
      "description": "Suscipit quaerat voluptate ipsam doloremque sit ut magnam repellat. Porro aliquam consequatur autem eaque maxime et praesentium voluptatem quod. Pariatur nam hic ad eveniet et. Quia et in molestias accusamus enim perferendis illo. Accusantium eveniet repudiandae neque et dolor.\n \rNihil laudantium quo et nam rerum laboriosam est necessitatibus non. Molestiae autem dolores corporis velit. Odio possimus in nemo autem et quibusdam ipsa alias ratione. Perferendis consectetur necessitatibus. Omnis inventore inventore. Molestiae est quos inventore aliquid quo sunt ex ea et.\n \rRecusandae quo officia in necessitatibus doloremque sapiente quam eligendi modi. Ratione deleniti minima delectus ut. Beatae esse et sit facere veniam culpa officia consequatur. Totam illo voluptatem esse blanditiis neque id numquam autem. Vel ipsa ea. Animi et et voluptates.",
      "sellerEmail": "Mckenzie21@hotmail.com",
      "sellerPhone": "+549 (72) 207-80-20",
      "sellerName": "Amaya Nikolaus",
      "sellerCompany": "Ankunding Inc",
      "id": 2,
      "imagesCount": 6
    },
    {
      "make": "Nam",
      "model": "Culpa",
      "price": 92239.59,
      "voted": 857,
      "rating": 1.21555969463967,
      "addedAt": "2020-06-11T09:58:15.772Z",
      "version": "Distinctio",
      "mileage": 224197,
      "carRegAt": "2018-04-19T10:00:11.001Z",
      "equipment": [
        "matrix",
        "transmitter",
        "matrix",
        "monitor",
        "feed",
        "panel",
        "transmitter",
        "monitor",
        "bandwidth",
        "sensor",
        "hard drive",
        "pixel",
        "monitor",
        "interface",
        "transmitter",
        "alarm",
        "program",
        "feed",
        "bus",
        "driver",
        "alarm",
        "monitor"
      ],
      "description": "Cum tempora sint eveniet dolorem nesciunt est assumenda consequuntur. Consequatur voluptate iusto similique et ut. Consequatur voluptatum natus. Esse odit est quis. Accusantium perferendis eum culpa architecto et ex.\n \rQuae sint aut consequuntur quasi nesciunt in. Et incidunt qui et autem. Eius inventore rem qui sit rerum est. Modi quas tenetur qui doloremque.\n \rSuscipit laborum accusantium non quia qui rerum voluptatem. Sint tenetur sunt sit minus amet. Pariatur maiores aut quod. Dolores dicta deleniti autem deserunt. Commodi sed omnis. Qui dolores quaerat.",
      "sellerEmail": "Davonte.Wuckert@yahoo.com",
      "sellerPhone": "+680 (01) 432-14-63",
      "sellerName": "Chaya Klein",
      "sellerCompany": "Legros - Howell",
      "id": 3,
      "imagesCount": 7
    },
    {
      "make": "Officia",
      "model": "Sit",
      "price": 11449.05,
      "voted": 48,
      "rating": 3.5109422126791223,
      "addedAt": "2020-06-11T01:40:59.714Z",
      "version": "Ipsam",
      "mileage": 170478,
      "carRegAt": "2018-04-09T09:28:00.848Z",
      "equipment": [
        "application",
        "sensor",
        "port",
        "program",
        "hard drive",
        "interface",
        "bandwidth",
        "system",
        "card"
      ],
      "description": "Omnis exercitationem exercitationem atque sint optio aut quia. Sapiente ipsum cumque ab voluptatem. In enim consequuntur nulla placeat ullam maxime voluptas et error. Fuga est et beatae.\n \rAb quod nam dolorum explicabo. Quos perspiciatis laborum qui necessitatibus similique dolor fugit earum voluptatibus. Est consequatur omnis corrupti. Aliquid ipsam dolor voluptatum repellat commodi ut.\n \rVoluptate saepe aut minima. Laborum consequatur nobis. Quaerat ad autem qui.",
      "sellerEmail": "Dejuan.Powlowski@hotmail.com",
      "sellerPhone": "+471 (35) 467-99-37",
      "sellerName": "Sofia Mante",
      "sellerCompany": "Kuphal, Paucek and Stanton",
      "id": 4,
      "imagesCount": 2
    },
    {
      "make": "Architecto",
      "model": "Et",
      "price": 65533.52,
      "voted": 193,
      "rating": 3.502935978156832,
      "addedAt": "2020-06-11T20:03:46.361Z",
      "version": "Nobis",
      "mileage": 139501,
      "carRegAt": "2017-03-24T14:21:03.964Z",
      "equipment": [
        "driver",
        "hard drive",
        "monitor",
        "protocol",
        "monitor",
        "capacitor",
        "feed",
        "panel",
        "hard drive",
        "system",
        "circuit",
        "hard drive",
        "driver",
        "circuit"
      ],
      "description": "Molestias ut itaque. Quisquam possimus cum assumenda voluptatum atque quam. Aut nobis id voluptate illum qui quod qui reprehenderit. Quia cum occaecati repellat. Dolorem quaerat harum magni quasi aut pariatur quaerat.\n \rEos aut et est. Eveniet eligendi nulla voluptas nihil inventore necessitatibus quia aut. Accusamus aut et fugit molestias.\n \rMaxime ullam dolores veritatis occaecati quasi autem. Esse quis vel nemo accusamus voluptatibus. Delectus mollitia ipsum quibusdam magnam dolores ut velit et voluptatem. Nostrum et laborum debitis est repudiandae rerum nihil voluptatem cumque.",
      "sellerEmail": "Brooklyn97@hotmail.com",
      "sellerPhone": "+592 (09) 869-69-85",
      "sellerName": "Rebeka Kautzer",
      "sellerCompany": "Kuhn, Pacocha and Murphy",
      "id": 5,
      "imagesCount": 5
    },
    {
      "make": "Dignissimos",
      "model": "Neque",
      "price": 51645.28,
      "voted": 408,
      "rating": 1.6416325502887323,
      "addedAt": "2020-06-11T22:57:39.135Z",
      "version": "Similique",
      "mileage": 286589,
      "carRegAt": "2015-08-21T23:52:36.981Z",
      "equipment": [
        "capacitor",
        "bandwidth",
        "hard drive",
        "alarm",
        "matrix",
        "panel",
        "firewall",
        "panel",
        "transmitter",
        "capacitor",
        "application",
        "bandwidth",
        "panel",
        "transmitter",
        "microchip",
        "driver",
        "application",
        "panel"
      ],
      "description": "Qui dolor dolores perferendis dolore molestias aspernatur. Illum consequuntur qui unde. Ducimus neque iusto sit quidem voluptatem voluptatem ut sed. Magnam quaerat repellat eum quo magni molestiae suscipit earum consequuntur. Rem sunt quos.\n \rLaudantium quam neque ad in. Ex dolorem impedit tenetur. Voluptas eum vero dolorum sint. Harum molestiae ut numquam.\n \rAccusamus maiores vel tempore doloribus quasi et non et. Esse rerum quo facere voluptatem et et animi rerum et. Non soluta repellat rem repellat.",
      "sellerEmail": "Sarai_Kozey@yahoo.com",
      "sellerPhone": "+094 (37) 935-36-88",
      "sellerName": "Rosella Davis",
      "sellerCompany": "Abernathy - Kuhn",
      "id": 6,
      "imagesCount": 7
    },
    {
      "make": "Praesentium",
      "model": "Enim",
      "price": 33128.3,
      "voted": 656,
      "rating": 2.3835286343021407,
      "addedAt": "2020-06-11T02:34:55.220Z",
      "version": "Doloremque",
      "mileage": 2578,
      "carRegAt": "2016-02-03T16:45:32.611Z",
      "equipment": [
        "bus",
        "interface",
        "panel",
        "driver",
        "transmitter",
        "protocol",
        "card",
        "hard drive",
        "monitor",
        "array",
        "pixel",
        "alarm"
      ],
      "description": "Veritatis voluptas enim autem ab repudiandae qui. Facilis eos beatae cum. Dolores magni impedit earum voluptatum.\n \rConsequatur ipsam totam quia officia debitis possimus molestiae. Et aut qui. Molestiae maiores sint adipisci ut distinctio aspernatur enim placeat explicabo. Eligendi non soluta sunt sed quam esse reprehenderit sint. Ut vel laboriosam.\n \rDeleniti consequatur id. Dolorem deleniti eum enim consectetur in repellendus blanditiis facere. Consequatur aut ut sunt rerum ducimus magnam illum tenetur doloremque. Vero quaerat rerum. Ipsa voluptatibus vitae est ad vel nostrum quas molestias eveniet. Quod deserunt nam porro enim at.",
      "sellerEmail": "Gerry84@hotmail.com",
      "sellerPhone": "+163 (58) 048-53-59",
      "sellerName": "Darren Abernathy",
      "sellerCompany": "Abernathy - Roberts",
      "id": 7,
      "imagesCount": 2
    },
    {
      "make": "Enim",
      "model": "Dolor",
      "price": 56779.63,
      "voted": 700,
      "rating": 3.1255047614512312,
      "addedAt": "2020-06-11T13:45:45.719Z",
      "version": "Et",
      "mileage": 141978,
      "carRegAt": "2016-03-05T21:50:05.180Z",
      "equipment": [
        "bus",
        "pixel",
        "firewall",
        "capacitor",
        "interface",
        "microchip",
        "card",
        "driver",
        "feed",
        "sensor",
        "matrix",
        "bus",
        "microchip",
        "driver",
        "pixel",
        "protocol",
        "interface",
        "protocol",
        "bus",
        "capacitor",
        "array",
        "card",
        "card",
        "port"
      ],
      "description": "Earum eaque vel fugiat esse sequi adipisci assumenda aut. Velit sed ut pariatur molestiae ipsa quidem. Ratione veritatis quis tempore exercitationem in autem illum aut. Nemo magni doloremque est. Omnis animi culpa.\n \rIn officia voluptatum et fugit rem tenetur modi odio nihil. Amet eveniet quia nostrum nulla ipsam quo et eos. Quae autem pariatur aut similique sit officiis maxime. Quia minus non sit quo amet. Officia veritatis sed cupiditate a officiis.\n \rNecessitatibus eos sequi cumque enim. Aut ipsam est eum. Autem aliquam corrupti odio vel suscipit minima totam. Qui voluptatem voluptatem ducimus et quam. Qui est maiores aut. Qui nulla molestiae aut iste.",
      "sellerEmail": "Providenci68@hotmail.com",
      "sellerPhone": "+577 (27) 959-12-50",
      "sellerName": "Moshe Considine",
      "sellerCompany": "Smith - Runolfsdottir",
      "id": 8,
      "imagesCount": 6
    },
    {
      "make": "Fuga",
      "model": "Harum",
      "price": 42708.59,
      "voted": 598,
      "rating": 3.4241914661394217,
      "addedAt": "2020-06-11T00:20:36.012Z",
      "version": "Et",
      "mileage": 233828,
      "carRegAt": "2019-09-11T02:25:57.153Z",
      "equipment": [
        "circuit",
        "matrix",
        "driver",
        "bus",
        "application",
        "port"
      ],
      "description": "Minima neque quae iure vero dolore dolorem ab in. Rerum sed temporibus sed maiores vero qui natus officia. Magni quasi nobis voluptatem possimus earum quaerat et voluptatem nesciunt. Adipisci dolore quasi quo alias ut eaque beatae est. Molestias minus aliquid quia blanditiis repellat enim quibusdam fuga.\n \rNostrum est iure nesciunt dicta porro sed voluptate et consequatur. Soluta nulla et. Ea sit nam corporis sunt officiis sint odio. Officia similique culpa ut ipsa eveniet aut ipsam ut. Necessitatibus error fugiat velit consectetur illo. Qui iure voluptatem amet.\n \rSimilique corporis veritatis. Recusandae ut possimus quisquam. Molestiae commodi animi est ad fuga et id quas officiis. Assumenda accusantium eligendi labore distinctio dolorem qui. Asperiores iusto sint. Ullam sapiente voluptatem voluptas nesciunt.",
      "sellerEmail": "Brandi89@gmail.com",
      "sellerPhone": "+774 (52) 517-98-49",
      "sellerName": "Kaycee Waters",
      "sellerCompany": "Nienow - Gibson",
      "id": 9,
      "imagesCount": 8
    }
  ]
}